{
  "main": {
    "id": "f53db405ee5e24f7",
    "type": "split",
    "children": [
      {
        "id": "221a3caa85cb10ad",
        "type": "tabs",
        "children": [
          {
            "id": "d3ccdb647b62f398",
            "type": "leaf",
            "state": {
              "type": "markdown",
              "state": {
                "file": "Esther/Esther Rosana Sophys/Pokemon/02 - Halay-Alae/Training Notes.md",
                "mode": "source",
                "source": false
              },
              "icon": "lucide-file",
              "title": "Training Notes"
            }
          },
          {
            "id": "43b3e0676a34f9c0",
            "type": "leaf",
            "state": {
              "type": "markdown",
              "state": {
                "file": "Esther/Esther Rosana Sophys/Pokemon/02 - Halay-Alae/Moves.md",
                "mode": "source",
                "source": false
              },
              "icon": "lucide-file",
              "title": "Moves"
            }
          },
          {
            "id": "e08b6e9d93d5e861",
            "type": "leaf",
            "state": {
              "type": "mk-space",
              "state": {
                "path": "Esther/Arcs-Narrative-Threads/Other Notes/Sophys Farm"
              },
              "icon": "lucide-file",
              "title": "Sophys Farm"
            }
          },
          {
            "id": "85d21505156e9beb",
            "type": "leaf",
            "state": {
              "type": "mk-space",
              "state": {
                "path": "/"
              },
              "icon": "lucide-file",
              "title": "ERS-Obs"
            }
          }
        ],
        "currentTab": 3
      }
    ],
    "direction": "vertical"
  },
  "left": {
    "id": "76638051dfe7b456",
    "type": "split",
    "children": [
      {
        "id": "1c4989c71a49aed1",
        "type": "tabs",
        "children": [
          {
            "id": "e8cc9f6d44e29734",
            "type": "leaf",
            "state": {
              "type": "file-explorer",
              "state": {
                "sortOrder": "alphabetical",
                "autoReveal": false
              },
              "icon": "lucide-folder-closed",
              "title": "Files"
            }
          },
          {
            "id": "f90cca17fa96a144",
            "type": "leaf",
            "state": {
              "type": "search",
              "state": {
                "query": "tag:#Seed-Planted",
                "matchingCase": false,
                "explainSearch": false,
                "collapseAll": false,
                "extraContext": false,
                "sortOrder": "alphabetical"
              },
              "icon": "lucide-search",
              "title": "Search"
            }
          },
          {
            "id": "014a3026e6b21e92",
            "type": "leaf",
            "state": {
              "type": "bookmarks",
              "state": {},
              "icon": "lucide-bookmark",
              "title": "Bookmarks"
            }
          },
          {
            "id": "2187f975bb95a8da",
            "type": "leaf",
            "state": {
              "type": "mk-path-view",
              "state": {},
              "icon": "layout-grid",
              "title": "Navigator"
            }
          }
        ],
        "currentTab": 3
      }
    ],
    "direction": "horizontal",
    "width": 360.5
  },
  "right": {
    "id": "d608898f6072a511",
    "type": "split",
    "children": [
      {
        "id": "eb85ffb146598329",
        "type": "tabs",
        "children": [
          {
            "id": "db16095320d340e0",
            "type": "leaf",
            "state": {
              "type": "backlink",
              "state": {
                "file": "Esther/Arcs-Narrative-Threads/Arc - Mirage in Ashes/Ashes of the Hunt/Ashes of the Hunt.md",
                "collapseAll": false,
                "extraContext": false,
                "sortOrder": "alphabetical",
                "showSearch": false,
                "searchQuery": "",
                "backlinkCollapsed": false,
                "unlinkedCollapsed": true
              },
              "icon": "links-coming-in",
              "title": "Backlinks for Ashes of the Hunt"
            }
          },
          {
            "id": "bf4fa3c38350a72d",
            "type": "leaf",
            "state": {
              "type": "outgoing-link",
              "state": {
                "file": "Esther/Esther Rosana Sophys/Pokemon/Pokemon.md",
                "linksCollapsed": false,
                "unlinkedCollapsed": true
              },
              "icon": "links-going-out",
              "title": "Outgoing links from Pokemon"
            }
          },
          {
            "id": "b7a2c074474f2821",
            "type": "leaf",
            "state": {
              "type": "tag",
              "state": {
                "sortOrder": "frequency",
                "useHierarchy": true,
                "showSearch": false,
                "searchQuery": ""
              },
              "icon": "lucide-tags",
              "title": "Tags"
            }
          },
          {
            "id": "fe7c0ee1319da99f",
            "type": "leaf",
            "state": {
              "type": "outline",
              "state": {
                "followCursor": false,
                "showSearch": false,
                "searchQuery": ""
              },
              "icon": "lucide-list",
              "title": "Outline"
            }
          },
          {
            "id": "325977677a770955",
            "type": "leaf",
            "state": {
              "type": "footnotes",
              "state": {},
              "icon": "lucide-file-signature",
              "title": "Footnotes"
            }
          },
          {
            "id": "fc52c46686428e47",
            "type": "leaf",
            "state": {
              "type": "git-view",
              "state": {},
              "icon": "git-pull-request",
              "title": "Source Control"
            }
          },
          {
            "id": "da178d33e74b6ed6",
            "type": "leaf",
            "state": {
              "type": "footnotes",
              "state": {
                "file": "Esther/Arcs-Narrative-Threads/Oblivia Training Arc/Act I.md"
              },
              "icon": "lucide-file-signature",
              "title": "Footnotes"
            }
          }
        ],
        "currentTab": 5
      }
    ],
    "direction": "horizontal",
    "width": 436.5
  },
  "left-ribbon": {
    "hiddenItems": {
      "switcher:Open quick switcher": false,
      "graph:Open graph view": false,
      "canvas:Create new canvas": false,
      "daily-notes:Open today's daily note": false,
      "templates:Insert template": false,
      "command-palette:Open command palette": false,
      "bases:Create new base": false,
      "obsidian-excalidraw-plugin:New drawing": false,
      "obsidian-git:Open Git source control": false,
      "obsidian-kanban:Create new board": false,
      "obsidian-full-calendar:Open Full Calendar": false,
      "table-editor-obsidian:Advanced Tables Toolbar": false,
      "custom-sort:Toggle custom sorting": false,
      "github-sync:Sync with Remote": false,
      "radial-timeline:Radial timeline": false,
      "obsidian42-brat:BRAT": false,
      "templater-obsidian:Templater": false
    }
  },
  "active": "85d21505156e9beb",
  "lastOpenFiles": [
    "README.md",
    "Tags",
    "Esther/Arcs-Narrative-Threads/Arcs-Narrative-Threads.md",
    "Vault.md",
    "Esther/Arcs-Narrative-Threads/Other Notes/Untitled.md",
    "Esther/Esther Rosana Sophys/J - Pokemon/05 - Kasriel/Moves.md",
    "Esther/Esther Rosana Sophys/J - Pokemon/02 - Halay-Alae/02 - Halay-Alae.md",
    "Esther/Esther Rosana Sophys/J - Pokemon/05 - Kasriel/05 - Kasriel.md",
    "Esther/Esther Rosana Sophys/J - Pokemon/06 - Baquile Nava/Moves.md",
    "Esther/Esther Rosana Sophys/J - Pokemon/07 - L'Basseau/Moves.md",
    "Esther/Esther Rosana Sophys/J - Pokemon/08 - La Bamba/Moves.md",
    "Esther/Esther Rosana Sophys/J - Pokemon/08 - La Bamba/08 - La Bamba.md",
    "Esther/Esther Rosana Sophys/J - Pokemon/09 - Istha Haqra/Moves.md",
    "Esther/Esther Rosana Sophys/J - Pokemon/01 - Pyrrha/01 - Pyrrha.md",
    "Esther/Arcs-Narrative-Threads/Other Notes/Sophys Farm/Sophys Farm.md",
    "Esther/Esther Rosana Sophys/J - Pokemon/02 - Halay-Alae/Training Notes.md",
    "Esther/Esther Rosana Sophys/J - Pokemon/04 - Maciera/Training Notes.md",
    "Esther/Esther Rosana Sophys/J - Pokemon/04 - Maciera/04 - Maciera.md",
    "Esther/Esther Rosana Sophys/J - Pokemon/01 - Pyrrha/Moves.md",
    "Esther/Esther Rosana Sophys/J - Pokemon/02 - Halay-Alae/Moves.md",
    "Esther/Esther Rosana Sophys/J - Pokemon/07 - L'Basseau/07 - L'Basseau.md",
    "Esther/Esther Rosana Sophys/J - Pokemon/01 - Pyrrha/Training Notes.md",
    "Esther/Esther Rosana Sophys/I - Relationships/I - Relationships.md",
    "Esther/Esther Rosana Sophys/Esther Rosana Sophys.md",
    "Esther/Esther Rosana Sophys/I - Relationships/Monty.md",
    "Esther/Esther Rosana Sophys/I - Relationships/Azumi.md",
    "Esther/Esther Rosana Sophys/I - Relationships/Nakano.md",
    "Esther/Esther Rosana Sophys/I - Relationships",
    "Pasted image 20260115134515.png",
    "Esther/Esther Rosana Sophys/J - Pokemon/02 - Halay-Alae",
    "Esther/Esther Rosana Sophys/J - Pokemon/02 - Halay-Alae",
    "Esther/Esther Rosana Sophys/J - Pokemon/02 - Halay-Alae",
    "Esther/Esther Rosana Sophys/J - Pokemon/10 - Jecroix",
    "Esther/Esther Rosana Sophys/J - Pokemon/09 - Istha Haqra",
    "Esther/Esther Rosana Sophys/J - Pokemon/08 - La Bamba",
    "Esther/Esther Rosana Sophys/J - Pokemon/06 - Baquile Nava",
    "Esther/Esther Rosana Sophys/J - Pokemon/07 - L'Basseau",
    "Esther/Arcs-Narrative-Threads/Antagonists/Pasted image 20251121081455.png",
    "TimelineSampleVault/Media/Pasted image 20230707162456.png",
    "TimelineSampleVault/Media/Pasted image 20230707162508.png",
    "TimelineSampleVault/Media/Pasted image 20230707161746.png",
    "TimelineSampleVault/Media/Pasted image 20230707161828.png",
    "TimelineSampleVault/Media/Pasted image 20230816134705.png",
    "TimelineSampleVault/Canvases/Conditional Formats.canvas",
    "TimelineSampleVault/Canvases/Basic usage.canvas",
    "TimelineSampleVault/Canvases/Basic concept.canvas",
    "ERS-Obsidian/Excalidraw/Untitled.canvas"
  ]
}